smth/__init__.py
smth/__main__.py
smth/cloud.py
smth/config.py
smth/const.py
smth/db.py
smth/main.py
smth/scanner.py
smth/validators.py
smth/view.py
smth/commands/__init__.py
smth/commands/command.py
smth/commands/create.py
smth/commands/delete.py
smth/commands/list.py
smth/commands/open.py
smth/commands/scan.py
smth/commands/share.py
smth/commands/types.py
smth/commands/update.py
smth/commands/upload.py
smth/models/__init__.py
smth/models/notebook.py
smth/models/notebook_type.py
smth-0.8.0.dist-info/LICENSE
smth-0.8.0.dist-info/METADATA
smth-0.8.0.dist-info/WHEEL
smth-0.8.0.dist-info/entry_points.txt
smth-0.8.0.dist-info/top_level.txt
smth-0.8.0.dist-info/RECORD
