Metadata-Version: 2.1
Name: smth
Version: 0.8.0
Summary: Scan books and handwriting in batch mode from console
Home-page: https://github.com/dmitrvk/smth
License: UNKNOWN
Keywords: scan sane cli
Platform: UNKNOWN
Classifier: Environment :: Console
Classifier: Intended Audience :: End Users/Desktop
Classifier: Programming Language :: Python :: 3.8
Classifier: Programming Language :: Python :: Implementation :: CPython
Classifier: License :: OSI Approved :: GNU General Public License v3 (GPLv3)
Classifier: Operating System :: POSIX :: Linux
Classifier: Topic :: Multimedia :: Graphics :: Capture :: Scanners
Requires-Python: >=3.8
Requires-Dist: fpdf (>=1.7)
Requires-Dist: PyInquirer (>=1.0)
Requires-Dist: Pillow (>=7.2)
Requires-Dist: python-sane (>=2.8)
